{"assets/fonts/SpecialElite.ttf":["assets/fonts/SpecialElite.ttf"],"assets/fonts/Staatliches.ttf":["assets/fonts/Staatliches.ttf"],"assets/images/Rock.png":["assets/images/Rock.png"],"assets/images/drums.png":["assets/images/drums.png"],"assets/images/grain.png":["assets/images/grain.png"],"assets/images/guitar.png":["assets/images/guitar.png"],"assets/images/jazz.png":["assets/images/jazz.png"],"assets/images/piano.png":["assets/images/piano.png"],"assets/images/pp.png":["assets/images/pp.png"],"assets/images/pp2.png":["assets/images/pp2.png"],"assets/sounds/A.mp3":["assets/sounds/A.mp3"],"assets/sounds/A_oct.mp3":["assets/sounds/A_oct.mp3"],"assets/sounds/A_sharp.mp3":["assets/sounds/A_sharp.mp3"],"assets/sounds/A_sharp_oct.mp3":["assets/sounds/A_sharp_oct.mp3"],"assets/sounds/B.mp3":["assets/sounds/B.mp3"],"assets/sounds/B_oct.mp3":["assets/sounds/B_oct.mp3"],"assets/sounds/C.mp3":["assets/sounds/C.mp3"],"assets/sounds/C_oct.mp3":["assets/sounds/C_oct.mp3"],"assets/sounds/C_sharp.mp3":["assets/sounds/C_sharp.mp3"],"assets/sounds/C_sharp_oct.mp3":["assets/sounds/C_sharp_oct.mp3"],"assets/sounds/D.mp3":["assets/sounds/D.mp3"],"assets/sounds/D_oct.mp3":["assets/sounds/D_oct.mp3"],"assets/sounds/D_sharp.mp3":["assets/sounds/D_sharp.mp3"],"assets/sounds/D_sharp_oct.mp3":["assets/sounds/D_sharp_oct.mp3"],"assets/sounds/E.mp3":["assets/sounds/E.mp3"],"assets/sounds/E_oct.mp3":["assets/sounds/E_oct.mp3"],"assets/sounds/F.mp3":["assets/sounds/F.mp3"],"assets/sounds/FX_piano13.mp3":["assets/sounds/FX_piano13.mp3"],"assets/sounds/F_oct.mp3":["assets/sounds/F_oct.mp3"],"assets/sounds/F_sharp.mp3":["assets/sounds/F_sharp.mp3"],"assets/sounds/F_sharp_oct.mp3":["assets/sounds/F_sharp_oct.mp3"],"assets/sounds/G.mp3":["assets/sounds/G.mp3"],"assets/sounds/G_oct.mp3":["assets/sounds/G_oct.mp3"],"assets/sounds/G_sharp.mp3":["assets/sounds/G_sharp.mp3"],"assets/sounds/G_sharp_oct.mp3":["assets/sounds/G_sharp_oct.mp3"],"assets/sounds/met.mp3":["assets/sounds/met.mp3"],"packages/cupertino_icons/assets/CupertinoIcons.ttf":["packages/cupertino_icons/assets/CupertinoIcons.ttf"]}